text_parser_utils/__init__.py
text_parser_utils/main.py
text_parser_utils/prompts.py
text_parser_utils-2025.12.21085136.dist-info/METADATA
text_parser_utils-2025.12.21085136.dist-info/WHEEL
text_parser_utils-2025.12.21085136.dist-info/top_level.txt
text_parser_utils-2025.12.21085136.dist-info/RECORD
