Metadata-Version: 2.4
Name: text-parser-utils
Version: 2025.12.21085136
Summary: A new package is designed to simplify user interactions by accepting free-text prompts and providing structured, reliable responses. It leverages an underlying pattern-matching system to interpret use
Author-email: text-parser-utils <hi@eugene.plus>
License: MIT
Project-URL: Homepage, https://github.com/chigwell/text-parser-utils
Requires-Python: >=3.9
Requires-Dist: langchain-llm7>=0.0.0
Requires-Dist: llmatch-messages>=0.0.0
Requires-Dist: langchain-core>=0.3.0
